sknw/__init__.py
sknw/sknw.py
sknw-0.15.dist-info/LICENSE
sknw-0.15.dist-info/METADATA
sknw-0.15.dist-info/WHEEL
sknw-0.15.dist-info/top_level.txt
sknw-0.15.dist-info/RECORD
